ai_code_security_auditor-2.0.0.dist-info/licenses/LICENSE
app/__init__.py
app/celery_app.py
app/config.py
app/main.py
app/monitoring.py
app/websocket_manager.py
app/agents/__init__.py
app/agents/security_agent.py
app/api/__init__.py
app/api/analytics_endpoints.py
app/api/async_endpoints.py
app/models/__init__.py
app/models/analytics.py
app/services/__init__.py
app/services/analytics_service.py
app/services/cache_service.py
app/services/git_service.py
app/services/llm_client.py
app/services/llm_service.py
app/services/rag_service.py
app/services/scanner.py
app/utils/formatters.py
app/utils/report_generator.py
app/utils/visualizations.py
app/workers/__init__.py
app/workers/repo_scan_worker.py
app/workers/scan_worker.py
auditor/__init__.py
auditor/cli.py
ai_code_security_auditor-2.0.0.dist-info/METADATA
ai_code_security_auditor-2.0.0.dist-info/WHEEL
ai_code_security_auditor-2.0.0.dist-info/entry_points.txt
ai_code_security_auditor-2.0.0.dist-info/top_level.txt
ai_code_security_auditor-2.0.0.dist-info/RECORD
