Metadata-Version: 2.4
Name: ai-code-security-auditor
Version: 2.0.0
Summary: AI-powered security scanner with multi-model LLM integration for comprehensive code vulnerability detection and automated patch generation
Author-email: AI Security Team <security@aiauditor.com>
License: MIT
Project-URL: Homepage, https://github.com/ai-security-team/ai-code-security-auditor
Project-URL: Documentation, https://ai-code-security-auditor.readthedocs.io
Project-URL: Repository, https://github.com/ai-security-team/ai-code-security-auditor.git
Project-URL: Bug Reports, https://github.com/ai-security-team/ai-code-security-auditor/issues
Project-URL: Changelog, https://github.com/ai-security-team/ai-code-security-auditor/blob/main/CHANGELOG.md
Keywords: security,vulnerability,scanner,ai,llm,openrouter,bandit,semgrep,cli,analytics,monitoring,devops
Classifier: Development Status :: 5 - Production/Stable
Classifier: Environment :: Console
Classifier: Environment :: Web Environment
Classifier: Intended Audience :: Developers
Classifier: Intended Audience :: System Administrators
Classifier: License :: OSI Approved :: MIT License
Classifier: Operating System :: OS Independent
Classifier: Programming Language :: Python :: 3
Classifier: Programming Language :: Python :: 3.11
Classifier: Programming Language :: Python :: 3.12
Classifier: Topic :: Security
Classifier: Topic :: Software Development :: Quality Assurance
Classifier: Topic :: Software Development :: Testing
Classifier: Topic :: System :: Monitoring
Requires-Python: >=3.11
License-File: LICENSE
Requires-Dist: fastapi>=0.104.0
Requires-Dist: uvicorn[standard]>=0.20.0
Requires-Dist: sqlalchemy>=2.0.0
Requires-Dist: alembic>=1.12.0
Requires-Dist: bandit>=1.7.5
Requires-Dist: semgrep>=1.45.0
Requires-Dist: langchain>=0.1.0
Requires-Dist: langchain-openai>=0.1.0
Requires-Dist: langgraph>=0.0.40
Requires-Dist: chromadb>=0.4.15
Requires-Dist: sentence-transformers>=2.2.2
Requires-Dist: httpx>=0.25.0
Requires-Dist: requests>=2.31.0
Requires-Dist: pytest>=7.4.0
Requires-Dist: pytest-asyncio>=0.21.0
Requires-Dist: python-multipart>=0.0.6
Requires-Dist: aiofiles>=23.2.1
Requires-Dist: pydantic-settings>=2.0.0
Requires-Dist: langchain-community>=0.0.20
Requires-Dist: langchain-core>=0.1.0
Requires-Dist: langchain-deepseek>=0.1.0
Requires-Dist: click>=8.1.7
Requires-Dist: gunicorn>=21.2.0
Requires-Dist: prometheus-client>=0.18.0
Requires-Dist: pathlib2>=2.3.7
Requires-Dist: redis>=4.5.0
Requires-Dist: celery[redis]>=5.3.0
Requires-Dist: kombu>=5.3.0
Requires-Dist: websockets>=11.0.3
Requires-Dist: python-socketio[asyncio-client]>=5.9.0
Requires-Dist: eventlet>=0.33.3
Requires-Dist: flower>=2.0.1
Requires-Dist: GitPython>=3.1.0
Requires-Dist: tqdm>=4.65.0
Requires-Dist: colorama>=0.4.6
Requires-Dist: pyyaml>=6.0
Requires-Dist: rich>=13.0.0
Provides-Extra: dev
Requires-Dist: pytest>=7.4.0; extra == "dev"
Requires-Dist: pytest-asyncio>=0.21.0; extra == "dev"
Requires-Dist: pytest-cov>=4.1.0; extra == "dev"
Requires-Dist: mypy>=1.5.1; extra == "dev"
Requires-Dist: black>=23.7.0; extra == "dev"
Requires-Dist: isort>=5.12.0; extra == "dev"
Requires-Dist: flake8>=6.0.0; extra == "dev"
Requires-Dist: pre-commit>=3.3.3; extra == "dev"
Provides-Extra: test
Requires-Dist: pytest>=7.4.0; extra == "test"
Requires-Dist: pytest-asyncio>=0.21.0; extra == "test"
Requires-Dist: pytest-cov>=4.1.0; extra == "test"
Requires-Dist: httpx>=0.25.0; extra == "test"
Requires-Dist: pytest-mock>=3.11.1; extra == "test"
Provides-Extra: docs
Requires-Dist: mkdocs>=1.5.0; extra == "docs"
Requires-Dist: mkdocs-material>=9.2.0; extra == "docs"
Requires-Dist: mkdocs-mermaid2-plugin>=1.1.1; extra == "docs"
Dynamic: license-file
